{"results": [{"id": "0000842717:2019:FY", "start_date": "2019-01-01", "end_date": "2019-12-31", "filing_date": "2020-04-14", "timeframe": "annual", "fiscal_period": "FY", "fiscal_year": "2019", "cik": "0000842717", "sic": "6022", "tickers": ["BRBS"], "company_name": "BLUE RIDGE BANKSHARES, INC.", "source_filing_url": "https://api.polygon.io/v1/reference/sec/filings/0001564590-20-016731", "source_filing_file_url": "http://api.polygon.io/v1/reference/sec/filings/0001564590-20-016731/files/brbs-20191231.xml", "financials": {"cash_flow_statement": {"net_cash_flow_from_investing_activities_continuing": {"value": -100180000.0, "unit": "USD", "label": "Net Cash Flow From Investing Activities, Continuing", "order": 500}, "net_cash_flow_continuing": {"value": 45000000.0, "unit": "USD", "label": "Net Cash Flow, Continuing", "order": 1200}, "net_cash_flow_from_financing_activities_continuing": {"value": 160265000.0, "unit": "USD", "label": "Net Cash Flow From Financing Activities, Continuing", "order": 800}, "net_cash_flow_from_financing_activities": {"value": 160265000.0, "unit": "USD", "label": "Net Cash Flow From Financing Activities", "order": 700}, "net_cash_flow_from_operating_activities": {"value": -15085000.0, "unit": "USD", "label": "Net Cash Flow From Operating Activities", "order": 100}, "net_cash_flow_from_investing_activities": {"value": -100180000.0, "unit": "USD", "label": "Net Cash Flow From Investing Activities", "order": 400}, "net_cash_flow": {"value": 45000000.0, "unit": "USD", "label": "Net Cash Flow", "order": 1100}, "net_cash_flow_from_operating_activities_continuing": {"value": -15085000.0, "unit": "USD", "label": "Net Cash Flow From Operating Activities, Continuing", "order": 200}}, "balance_sheet": {"equity": {"value": 92337000.0, "unit": "USD", "label": "Equity", "order": 1400}, "other_than_fixed_noncurrent_assets": {"value": -13651000.0, "unit": "USD", "label": "Other Than Fixed Noncurrent Assets", "order": 500}, "noncurrent_assets": {"value": 0, "unit": "USD", "label": "Noncurrent Assets", "order": 300}, "liabilities": {"value": 868474000.0, "unit": "USD", "label": "Liabilities", "order": 600}, "fixed_assets": {"value": 13651000.0, "unit": "USD", "label": "Fixed Assets", "order": 400}, "liabilities_and_equity": {"value": 960811000.0, "unit": "USD", "label": "Liabilities And Equity", "order": 1900}, "current_liabilities": {"value": 868474000.0, "unit": "USD", "label": "Current Liabilities", "order": 700}, "noncurrent_liabilities": {"value": 0, "unit": "USD", "label": "Noncurrent Liabilities", "order": 800}, "assets": {"value": 960811000.0, "unit": "USD", "label": "Assets", "order": 100}, "current_assets": {"value": 960811000.0, "unit": "USD", "label": "Current Assets", "order": 200}, "equity_attributable_to_noncontrolling_interest": {"value": 224000, "unit": "USD", "label": "Equity Attributable To Noncontrolling Interest", "order": 1500}, "equity_attributable_to_parent": {"value": 92113000.0, "unit": "USD", "label": "Equity Attributable To Parent", "order": 1600}}, "comprehensive_income": {"other_comprehensive_income_loss": {"value": 847000, "unit": "USD", "label": "Other Comprehensive Income/Loss", "order": 400}, "comprehensive_income_loss": {"value": 5451000.0, "unit": "USD", "label": "Comprehensive Income/Loss", "order": 100}, "comprehensive_income_loss_attributable_to_parent": {"value": 5427000.0, "unit": "USD", "label": "Comprehensive Income/Loss Attributable To Parent", "order": 300}, "comprehensive_income_loss_attributable_to_noncontrolling_interest": {"value": 24000, "unit": "USD", "label": "Comprehensive Income/Loss Attributable To Noncontrolling Interest", "order": 200}}, "income_statement": {"operating_income_loss": {"value": 5577000.0, "unit": "USD", "label": "Operating Income/Loss", "order": 1100}, "costs_and_expenses": {"value": 44106000.0, "unit": "USD", "label": "Costs And Expenses", "order": 600}, "net_income_loss_attributable_to_noncontrolling_interest": {"value": 24000, "unit": "USD", "label": "Net Income/Loss Attributable To Noncontrolling Interest", "order": 3300}, "preferred_stock_dividends_and_other_adjustments": {"value": 0, "unit": "USD", "label": "Preferred Stock Dividends And Other Adjustments", "order": 3900}, "income_loss_from_continuing_operations_before_tax": {"value": 5577000.0, "unit": "USD", "label": "Income/Loss From Continuing Operations Before Tax", "order": 1500}, "income_loss_before_equity_method_investments": {"value": 5577000.0, "unit": "USD", "label": "Income/Loss Before Equity Method Investments", "order": 1300}, "revenues": {"value": 49683000.0, "unit": "USD", "label": "Revenues", "order": 100}, "net_income_loss": {"value": 4604000.0, "unit": "USD", "label": "Net Income/Loss", "order": 3200}, "noninterest_income": {"value": 18796000.0, "unit": "USD", "label": "Noninterest Income", "order": 3100}, "basic_earnings_per_share": {"value": 1.1, "unit": "USD / shares", "label": "Basic Earnings Per Share", "order": 4200}, "interest_and_dividend_income_operating": {"value": 30888000.0, "unit": "USD", "label": "Interest And Dividend Income, Operating", "order": 2600}, "interest_income_expense_after_provision_for_losses": {"value": 19626000.0, "unit": "USD", "label": "Interest Income/Expense After Provision For Losses", "order": 2800}, "participating_securities_distributed_and_undistributed_earnings_loss_basic": {"value": 0, "unit": "USD", "label": "Participating Securities, Distributed And Undistributed Earnings/Loss, Basic", "order": 3800}, "income_tax_expense_benefit_deferred": {"value": -85000, "unit": "USD", "label": "Income Tax Expense/Benefit, Deferred", "order": 2400}, "income_loss_from_continuing_operations_after_tax": {"value": 4604000.0, "unit": "USD", "label": "Income/Loss From Continuing Operations After Tax", "order": 1400}, "benefits_costs_expenses": {"value": 44106000.0, "unit": "USD", "label": "Benefits Costs and Expenses", "order": 200}, "interest_expense_operating": {"value": 9520000.0, "unit": "USD", "label": "Interest Expense, Operating", "order": 2700}, "operating_expenses": {"value": 44106000.0, "unit": "USD", "label": "Operating Expenses", "order": 1000}, "interest_income_expense_operating_net": {"value": 21368000.0, "unit": "USD", "label": "Interest Income/Expense Operating, Net", "order": 2900}, "noninterest_expense": {"value": 32845000.0, "unit": "USD", "label": "Noninterest Expense", "order": 3000}, "net_income_loss_attributable_to_parent": {"value": 4580000.0, "unit": "USD", "label": "Net Income/Loss Attributable To Parent", "order": 3500}, "diluted_earnings_per_share": {"value": 1.1, "unit": "USD / shares", "label": "Diluted Earnings Per Share", "order": 4300}, "income_tax_expense_benefit": {"value": 973000, "unit": "USD", "label": "Income Tax Expense/Benefit", "order": 2200}, "net_income_loss_available_to_common_stockholders_basic": {"value": 4580000.0, "unit": "USD", "label": "Net Income/Loss Available To Common Stockholders, Basic", "order": 3700}, "income_tax_expense_benefit_current": {"value": 1058000.0, "unit": "USD", "label": "Income Tax Expense/Benefit, Current", "order": 2300}, "provision_for_loan_lease_and_other_losses": {"value": 1742000.0, "unit": "USD", "label": "Provision For Loan, Lease, And Other Losses", "order": 4000}}}}, {"id": "0000842717:2020:FY", "start_date": "2020-01-01", "end_date": "2020-12-31", "filing_date": "2021-03-29", "timeframe": "annual", "fiscal_period": "FY", "fiscal_year": "2020", "cik": "0000842717", "sic": "6022", "tickers": ["BRBS"], "company_name": "BLUE RIDGE BANKSHARES, INC.", "source_filing_url": "https://api.polygon.io/v1/reference/sec/filings/0001564590-21-016162", "source_filing_file_url": "http://api.polygon.io/v1/reference/sec/filings/0001564590-21-016162/files/brbs-20201231.xml", "financials": {"comprehensive_income": {"comprehensive_income_loss_attributable_to_noncontrolling_interest": {"value": 1000, "unit": "USD", "label": "Comprehensive Income/Loss Attributable To Noncontrolling Interest", "order": 200}, "other_comprehensive_income_loss": {"value": 35000, "unit": "USD", "label": "Other Comprehensive Income/Loss", "order": 400}, "comprehensive_income_loss_attributable_to_parent": {"value": 17731000.0, "unit": "USD", "label": "Comprehensive Income/Loss Attributable To Parent", "order": 300}, "comprehensive_income_loss": {"value": 17732000.0, "unit": "USD", "label": "Comprehensive Income/Loss", "order": 100}}, "income_statement": {"operating_expenses": {"value": 88787000.0, "unit": "USD", "label": "Operating Expenses", "order": 1000}, "net_income_loss": {"value": 17697000.0, "unit": "USD", "label": "Net Income/Loss", "order": 3200}, "operating_income_loss": {"value": 22497000.0, "unit": "USD", "label": "Operating Income/Loss", "order": 1100}, "noninterest_income": {"value": 56824000.0, "unit": "USD", "label": "Noninterest Income", "order": 3100}, "income_loss_before_equity_method_investments": {"value": 22497000.0, "unit": "USD", "label": "Income/Loss Before Equity Method Investments", "order": 1300}, "net_income_loss_attributable_to_parent": {"value": 17696000.0, "unit": "USD", "label": "Net Income/Loss Attributable To Parent", "order": 3500}, "income_loss_from_continuing_operations_after_tax": {"value": 17697000.0, "unit": "USD", "label": "Income/Loss From Continuing Operations After Tax", "order": 1400}, "income_loss_from_continuing_operations_before_tax": {"value": 22497000.0, "unit": "USD", "label": "Income/Loss From Continuing Operations Before Tax", "order": 1500}, "provision_for_loan_lease_and_other_losses": {"value": 10450000.0, "unit": "USD", "label": "Provision For Loan, Lease, And Other Losses", "order": 4000}, "costs_and_expenses": {"value": 88787000.0, "unit": "USD", "label": "Costs And Expenses", "order": 600}, "net_income_loss_available_to_common_stockholders_basic": {"value": 17696000.0, "unit": "USD", "label": "Net Income/Loss Available To Common Stockholders, Basic", "order": 3700}, "income_tax_expense_benefit_deferred": {"value": -1680000.0, "unit": "USD", "label": "Income Tax Expense/Benefit, Deferred", "order": 2400}, "basic_earnings_per_share": {"value": 3.11, "unit": "USD / shares", "label": "Basic Earnings Per Share", "order": 4200}, "income_tax_expense_benefit": {"value": 4800000.0, "unit": "USD", "label": "Income Tax Expense/Benefit", "order": 2200}, "interest_income_expense_operating_net": {"value": 44510000.0, "unit": "USD", "label": "Interest Income/Expense Operating, Net", "order": 2900}, "interest_and_dividend_income_operating": {"value": 54460000.0, "unit": "USD", "label": "Interest And Dividend Income, Operating", "order": 2600}, "revenues": {"value": 111284000.0, "unit": "USD", "label": "Revenues", "order": 100}, "diluted_earnings_per_share": {"value": 3.11, "unit": "USD / shares", "label": "Diluted Earnings Per Share", "order": 4300}, "benefits_costs_expenses": {"value": 88787000.0, "unit": "USD", "label": "Benefits Costs and Expenses", "order": 200}, "preferred_stock_dividends_and_other_adjustments": {"value": 0, "unit": "USD", "label": "Preferred Stock Dividends And Other Adjustments", "order": 3900}, "noninterest_expense": {"value": 68387000.0, "unit": "USD", "label": "Noninterest Expense", "order": 3000}, "interest_expense_operating": {"value": 9950000.0, "unit": "USD", "label": "Interest Expense, Operating", "order": 2700}, "participating_securities_distributed_and_undistributed_earnings_loss_basic": {"value": 0, "unit": "USD", "label": "Participating Securities, Distributed And Undistributed Earnings/Loss, Basic", "order": 3800}, "interest_income_expense_after_provision_for_losses": {"value": 34060000.0, "unit": "USD", "label": "Interest Income/Expense After Provision For Losses", "order": 2800}, "net_income_loss_attributable_to_noncontrolling_interest": {"value": 1000, "unit": "USD", "label": "Net Income/Loss Attributable To Noncontrolling Interest", "order": 3300}}, "balance_sheet": {"equity_attributable_to_noncontrolling_interest": {"value": 225000, "unit": "USD", "label": "Equity Attributable To Noncontrolling Interest", "order": 1500}, "fixed_assets": {"value": 14831000.0, "unit": "USD", "label": "Fixed Assets", "order": 400}, "liabilities_and_equity": {"value": 1498258000.0, "unit": "USD", "label": "Liabilities And Equity", "order": 1900}, "current_assets": {"value": 1498258000.0, "unit": "USD", "label": "Current Assets", "order": 200}, "noncurrent_liabilities": {"value": 0, "unit": "USD", "label": "Noncurrent Liabilities", "order": 800}, "noncurrent_assets": {"value": 0, "unit": "USD", "label": "Noncurrent Assets", "order": 300}, "assets": {"value": 1498258000.0, "unit": "USD", "label": "Assets", "order": 100}, "liabilities": {"value": 1390058000.0, "unit": "USD", "label": "Liabilities", "order": 600}, "current_liabilities": {"value": 1390058000.0, "unit": "USD", "label": "Current Liabilities", "order": 700}, "equity_attributable_to_parent": {"value": 107975000.0, "unit": "USD", "label": "Equity Attributable To Parent", "order": 1600}, "equity": {"value": 108200000.0, "unit": "USD", "label": "Equity", "order": 1400}, "other_than_fixed_noncurrent_assets": {"value": -14831000.0, "unit": "USD", "label": "Other Than Fixed Noncurrent Assets", "order": 500}}, "cash_flow_statement": {"net_cash_flow_from_financing_activities_continuing": {"value": 507144000.0, "unit": "USD", "label": "Net Cash Flow From Financing Activities, Continuing", "order": 800}, "net_cash_flow_from_financing_activities": {"value": 507144000.0, "unit": "USD", "label": "Net Cash Flow From Financing Activities", "order": 700}, "net_cash_flow_continuing": {"value": 57919000.0, "unit": "USD", "label": "Net Cash Flow, Continuing", "order": 1200}, "net_cash_flow": {"value": 57919000.0, "unit": "USD", "label": "Net Cash Flow", "order": 1100}, "net_cash_flow_from_operating_activities": {"value": -108340000.0, "unit": "USD", "label": "Net Cash Flow From Operating Activities", "order": 100}, "net_cash_flow_from_operating_activities_continuing": {"value": -108340000.0, "unit": "USD", "label": "Net Cash Flow From Operating Activities, Continuing", "order": 200}, "net_cash_flow_from_investing_activities": {"value": -340885000.0, "unit": "USD", "label": "Net Cash Flow From Investing Activities", "order": 400}, "net_cash_flow_from_investing_activities_continuing": {"value": -340885000.0, "unit": "USD", "label": "Net Cash Flow From Investing Activities, Continuing", "order": 500}}}}, {"id": "0000842717:2021:FY", "start_date": "2021-01-01", "end_date": "2021-12-31", "filing_date": "2022-03-11", "timeframe": "annual", "fiscal_period": "FY", "fiscal_year": "2021", "cik": "0000842717", "sic": "6022", "tickers": ["BRBS"], "company_name": "BLUE RIDGE BANKSHARES, INC.", "source_filing_url": "https://api.polygon.io/v1/reference/sec/filings/0000950170-22-003459", "source_filing_file_url": "http://api.polygon.io/v1/reference/sec/filings/0000950170-22-003459/files/brbs-20211231_htm.xml", "financials": {"cash_flow_statement": {"net_cash_flow_from_investing_activities_continuing": {"value": 52484000.0, "unit": "USD", "label": "Net Cash Flow From Investing Activities, Continuing", "order": 500}, "net_cash_flow_from_financing_activities": {"value": -99094000.0, "unit": "USD", "label": "Net Cash Flow From Financing Activities", "order": 700}, "net_cash_flow_from_operating_activities": {"value": 59308000.0, "unit": "USD", "label": "Net Cash Flow From Operating Activities", "order": 100}, "net_cash_flow_from_financing_activities_continuing": {"value": -99094000.0, "unit": "USD", "label": "Net Cash Flow From Financing Activities, Continuing", "order": 800}, "net_cash_flow_continuing": {"value": 12698000.0, "unit": "USD", "label": "Net Cash Flow, Continuing", "order": 1200}, "net_cash_flow_from_investing_activities": {"value": 52484000.0, "unit": "USD", "label": "Net Cash Flow From Investing Activities", "order": 400}, "net_cash_flow": {"value": 12698000.0, "unit": "USD", "label": "Net Cash Flow", "order": 1100}, "net_cash_flow_from_operating_activities_continuing": {"value": 59308000.0, "unit": "USD", "label": "Net Cash Flow From Operating Activities, Continuing", "order": 200}}, "balance_sheet": {"other_than_fixed_noncurrent_assets": {"value": -26661000.0, "unit": "USD", "label": "Other Than Fixed Noncurrent Assets", "order": 500}, "assets": {"value": 2665139000.0, "unit": "USD", "label": "Assets", "order": 100}, "liabilities": {"value": 2388000000.0, "unit": "USD", "label": "Liabilities", "order": 600}, "noncurrent_assets": {"value": 0, "unit": "USD", "label": "Noncurrent Assets", "order": 300}, "equity_attributable_to_parent": {"value": 276911000.0, "unit": "USD", "label": "Equity Attributable To Parent", "order": 1600}, "current_assets": {"value": 2665139000.0, "unit": "USD", "label": "Current Assets", "order": 200}, "current_liabilities": {"value": 2388000000.0, "unit": "USD", "label": "Current Liabilities", "order": 700}, "liabilities_and_equity": {"value": 2665139000.0, "unit": "USD", "label": "Liabilities And Equity", "order": 1900}, "noncurrent_liabilities": {"value": 0, "unit": "USD", "label": "Noncurrent Liabilities", "order": 800}, "equity": {"value": 277139000.0, "unit": "USD", "label": "Equity", "order": 1400}, "fixed_assets": {"value": 26661000.0, "unit": "USD", "label": "Fixed Assets", "order": 400}, "equity_attributable_to_noncontrolling_interest": {"value": 228000, "unit": "USD", "label": "Equity Attributable To Noncontrolling Interest", "order": 1500}}, "comprehensive_income": {"comprehensive_income_loss": {"value": 48584000.0, "unit": "USD", "label": "Comprehensive Income/Loss", "order": 100}, "other_comprehensive_income_loss": {"value": -3896000.0, "unit": "USD", "label": "Other Comprehensive Income/Loss", "order": 400}, "comprehensive_income_loss_attributable_to_parent": {"value": 48581000.0, "unit": "USD", "label": "Comprehensive Income/Loss Attributable To Parent", "order": 300}, "comprehensive_income_loss_attributable_to_noncontrolling_interest": {"value": 3000, "unit": "USD", "label": "Comprehensive Income/Loss Attributable To Noncontrolling Interest", "order": 200}}, "income_statement": {"operating_expenses": {"value": 35369000.0, "unit": "USD", "label": "Operating Expenses", "order": 1000}, "interest_income_expense_after_provision_for_losses": {"value": 92364000.0, "unit": "USD", "label": "Interest Income/Expense After Provision For Losses", "order": 2800}, "costs_and_expenses": {"value": 35369000.0, "unit": "USD", "label": "Costs And Expenses", "order": 600}, "net_income_loss_attributable_to_noncontrolling_interest": {"value": -3000, "unit": "USD", "label": "Net Income/Loss Attributable To Noncontrolling Interest", "order": 3300}, "provision_for_loan_lease_and_other_losses": {"value": 117000, "unit": "USD", "label": "Provision For Loan, Lease, And Other Losses", "order": 4000}, "noninterest_income": {"value": 87955000.0, "unit": "USD", "label": "Noninterest Income", "order": 3100}, "interest_and_dividend_income_operating": {"value": 103546000.0, "unit": "USD", "label": "Interest And Dividend Income, Operating", "order": 2600}, "preferred_stock_dividends_and_other_adjustments": {"value": 0, "unit": "USD", "label": "Preferred Stock Dividends And Other Adjustments", "order": 3900}, "net_income_loss_available_to_common_stockholders_basic": {"value": 52477000.0, "unit": "USD", "label": "Net Income/Loss Available To Common Stockholders, Basic", "order": 3700}, "benefits_costs_expenses": {"value": 35369000.0, "unit": "USD", "label": "Benefits Costs and Expenses", "order": 200}, "noninterest_expense": {"value": 112142000.0, "unit": "USD", "label": "Noninterest Expense", "order": 3000}, "net_income_loss_attributable_to_parent": {"value": 52477000.0, "unit": "USD", "label": "Net Income/Loss Attributable To Parent", "order": 3500}, "participating_securities_distributed_and_undistributed_earnings_loss_basic": {"value": 0, "unit": "USD", "label": "Participating Securities, Distributed And Undistributed Earnings/Loss, Basic", "order": 3800}, "income_loss_from_continuing_operations_after_tax": {"value": 52480000.0, "unit": "USD", "label": "Income/Loss From Continuing Operations After Tax", "order": 1400}, "income_tax_expense_benefit": {"value": 15697000.0, "unit": "USD", "label": "Income Tax Expense/Benefit", "order": 2200}, "interest_expense_operating": {"value": 11065000.0, "unit": "USD", "label": "Interest Expense, Operating", "order": 2700}, "interest_income_expense_operating_net": {"value": 92481000.0, "unit": "USD", "label": "Interest Income/Expense Operating, Net", "order": 2900}, "revenues": {"value": 103546000.0, "unit": "USD", "label": "Revenues", "order": 100}, "income_tax_expense_benefit_deferred": {"value": 1923000.0, "unit": "USD", "label": "Income Tax Expense/Benefit, Deferred", "order": 2400}, "net_income_loss": {"value": 52480000.0, "unit": "USD", "label": "Net Income/Loss", "order": 3200}, "income_loss_from_continuing_operations_before_tax": {"value": 68177000.0, "unit": "USD", "label": "Income/Loss From Continuing Operations Before Tax", "order": 1500}, "operating_income_loss": {"value": 68177000.0, "unit": "USD", "label": "Operating Income/Loss", "order": 1100}, "income_tax_expense_benefit_current": {"value": -30000, "unit": "USD", "label": "Income Tax Expense/Benefit, Current", "order": 2300}}}}], "status": "OK", "request_id": "6c685e8948fd795c7e6ec51341a9d049"}